{
  "courses": [
    {
      "name": "BUS101",
      "term": 1,
      "prerequisites": [

      ],
      "corequisites": [

      ],
      "credits": 3,
      "passrate": 0.0
    },
    {
      "name": "MATH111",
      "term": 1,
      "prerequisites": [
        "MATH100"
      ],
      "corequisites": [

      ],
      "credits": 4,
      "passrate": 0.0
    },
    {
      "name": "PSY201",
      "term": 1,
      "prerequisites": [

      ],
      "corequisites": [

      ],
      "credits": 3,
      "passrate": 0.0
    },
    {
      "name": "WRI121",
      "term": 1,
      "prerequisites": [

      ],
      "corequisites": [

      ],
      "credits": 3,
      "passrate": 0.0
    },
    {
      "name": "LAB SCI",
      "term": 1,
      "prerequisites": [

      ],
      "corequisites": [

      ],
      "credits": 4,
      "passrate": 0.0
    },
    {
      "name": "BUS215",
      "term": 2,
      "prerequisites": [

      ],
      "corequisites": [

      ],
      "credits": 3,
      "passrate": 0.0
    },
    {
      "name": "ECO201",
      "term": 2,
      "prerequisites": [
        "MATH111"
      ],
      "corequisites": [

      ],
      "credits": 3,
      "passrate": 0.0
    },
    {
      "name": "MIS102",
      "term": 2,
      "prerequisites": [

      ],
      "corequisites": [

      ],
      "credits": 1,
      "passrate": 0.0
    },
    {
      "name": "SPE111",
      "term": 2,
      "prerequisites": [

      ],
      "corequisites": [

      ],
      "credits": 3,
      "passrate": 0.0
    },
    {
      "name": "WRI122",
      "term": 2,
      "prerequisites": [
        "WRI121"
      ],
      "corequisites": [

      ],
      "credits": 3,
      "passrate": 0.0
    },
    {
      "name": "ELEC",
      "term": 2,
      "prerequisites": [

      ],
      "corequisites": [

      ],
      "credits": 3,
      "passrate": 0.0
    },
    {
      "name": "ECO202",
      "term": 3,
      "prerequisites": [
        "MATH111"
      ],
      "corequisites": [

      ],
      "credits": 3,
      "passrate": 0.0
    },
    {
      "name": "MIS206",
      "term": 3,
      "prerequisites": [

      ],
      "corequisites": [

      ],
      "credits": 3,
      "passrate": 0.0
    },
    {
      "name": "SPE321",
      "term": 3,
      "prerequisites": [
        "SPE111"
      ],
      "corequisites": [

      ],
      "credits": 3,
      "passrate": 0.0
    },
    {
      "name": "WRI227",
      "term": 3,
      "prerequisites": [
        "WRI122"
      ],
      "corequisites": [
        "SPE111"
      ],
      "credits": 3,
      "passrate": 0.0
    },
    {
      "name": "HUM",
      "term": 3,
      "prerequisites": [

      ],
      "corequisites": [

      ],
      "credits": 3,
      "passrate": 0.0
    },
    {
      "name": "ACC201",
      "term": 4,
      "prerequisites": [
        "MATH100"
      ],
      "corequisites": [

      ],
      "credits": 4,
      "passrate": 0.0
    },
    {
      "name": "BUS223",
      "term": 4,
      "prerequisites": [

      ],
      "corequisites": [

      ],
      "credits": 3,
      "passrate": 0.0
    },
    {
      "name": "MATH361",
      "term": 4,
      "prerequisites": [
        "MATH111"
      ],
      "corequisites": [

      ],
      "credits": 4,
      "passrate": 0.0
    },
    {
      "name": "MIS113",
      "term": 4,
      "prerequisites": [

      ],
      "corequisites": [

      ],
      "credits": 3,
      "passrate": 0.0
    },
    {
      "name": "BUS256",
      "term": 5,
      "prerequisites": [
        "BUS101",
        "WRI122"
      ],
      "corequisites": [

      ],
      "credits": 3,
      "passrate": 0.0
    },
    {
      "name": "BUS318",
      "term": 5,
      "prerequisites": [
        "BUS223",
        "PSY201"
      ],
      "corequisites": [

      ],
      "credits": 3,
      "passrate": 0.0
    },
    {
      "name": "BUS349",
      "term": 5,
      "prerequisites": [
        "BUS215"
      ],
      "corequisites": [

      ],
      "credits": 4,
      "passrate": 0.0
    },
    {
      "name": "MATH371",
      "term": 5,
      "prerequisites": [
        "MATH111"
      ],
      "corequisites": [

      ],
      "credits": 4,
      "passrate": 0.0
    },
    {
      "name": "PHIL342",
      "term": 5,
      "prerequisites": [
        "WRI122"
      ],
      "corequisites": [

      ],
      "credits": 3,
      "passrate": 0.0
    },
    {
      "name": "ACC203",
      "term": 6,
      "prerequisites": [
        "ACC201"
      ],
      "corequisites": [

      ],
      "credits": 4,
      "passrate": 0.0
    },
    {
      "name": "BUS397",
      "term": 6,
      "prerequisites": [
        "BUS349"
      ],
      "corequisites": [

      ],
      "credits": 3,
      "passrate": 0.0
    },
    {
      "name": "MIS225",
      "term": 6,
      "prerequisites": [

      ],
      "corequisites": [

      ],
      "credits": 4,
      "passrate": 0.0
    },
    {
      "name": "ELEC",
      "term": 6,
      "prerequisites": [

      ],
      "corequisites": [

      ],
      "credits": 3,
      "passrate": 0.0
    },
    {
      "name": "BUS314",
      "term": 7,
      "prerequisites": [
        "BUS215",
        "ACC203",
        "BUS223"
      ],
      "corequisites": [

      ],
      "credits": 3,
      "passrate": 0.0
    },
    {
      "name": "BUS356",
      "term": 7,
      "prerequisites": [
        "SPE111",
        "WRI122"
      ],
      "corequisites": [

      ],
      "credits": 4,
      "passrate": 0.0
    },
    {
      "name": "BUS467",
      "term": 7,
      "prerequisites": [
        "BUS215"
      ],
      "corequisites": [

      ],
      "credits": 3,
      "passrate": 0.0
    },
    {
      "name": "MGT321",
      "term": 7,
      "prerequisites": [
        "BUS215"
      ],
      "corequisites": [

      ],
      "credits": 3,
      "passrate": 0.0
    },
    {
      "name": "MIS375",
      "term": 7,
      "prerequisites": [
        "MIS102",
        "MATH361",
        "MATH371"
      ],
      "corequisites": [

      ],
      "credits": 3,
      "passrate": 0.0
    },
    {
      "name": "ACC245",
      "term": 8,
      "prerequisites": [
        "ACC201"
      ],
      "corequisites": [

      ],
      "credits": 3,
      "passrate": 0.0
    },
    {
      "name": "ACC325",
      "term": 8,
      "prerequisites": [
        "ACC203",
        "MATH111"
      ],
      "corequisites": [

      ],
      "credits": 4,
      "passrate": 0.0
    },
    {
      "name": "BUS226",
      "term": 8,
      "prerequisites": [

      ],
      "corequisites": [

      ],
      "credits": 3,
      "passrate": 0.0
    },
    {
      "name": "BUS335",
      "term": 8,
      "prerequisites": [
        "BUS314"
      ],
      "corequisites": [

      ],
      "credits": 3,
      "passrate": 0.0
    },
    {
      "name": "COMM",
      "term": 8,
      "prerequisites": [

      ],
      "corequisites": [

      ],
      "credits": 3,
      "passrate": 0.0
    },
    {
      "name": "ACC205",
      "term": 9,
      "prerequisites": [
        "ACC201"
      ],
      "corequisites": [

      ],
      "credits": 3,
      "passrate": 0.0
    },
    {
      "name": "BUS456",
      "term": 9,
      "prerequisites": [
        "MATH361",
        "WRI227"
      ],
      "corequisites": [

      ],
      "credits": 3,
      "passrate": 0.0
    },
    {
      "name": "MGT335",
      "term": 9,
      "prerequisites": [
        "BUS215"
      ],
      "corequisites": [

      ],
      "credits": 3,
      "passrate": 0.0
    },
    {
      "name": "ELEC",
      "term": 9,
      "prerequisites": [

      ],
      "corequisites": [

      ],
      "credits": 3,
      "passrate": 0.0
    },
    {
      "name": "ELEC",
      "term": 9,
      "prerequisites": [

      ],
      "corequisites": [

      ],
      "credits": 3,
      "passrate": 0.0
    },
    {
      "name": "BUS308",
      "term": 10,
      "prerequisites": [
        "WRI121"
      ],
      "corequisites": [

      ],
      "credits": 3,
      "passrate": 0.0
    },
    {
      "name": "BUS495",
      "term": 10,
      "prerequisites": [
        "MGT335",
        "BUS456"
      ],
      "corequisites": [

      ],
      "credits": 1,
      "passrate": 0.0
    },
    {
      "name": "BUS441",
      "term": 10,
      "prerequisites": [
        "BUS349"
      ],
      "corequisites": [

      ],
      "credits": 3,
      "passrate": 0.0
    },
    {
      "name": "PSY347",
      "term": 10,
      "prerequisites": [

      ],
      "corequisites": [

      ],
      "credits": 3,
      "passrate": 0.0
    },
    {
      "name": "HUM",
      "term": 10,
      "prerequisites": [

      ],
      "corequisites": [

      ],
      "credits": 3,
      "passrate": 0.0
    },
    {
      "name": "ELEC",
      "term": 10,
      "prerequisites": [

      ],
      "corequisites": [

      ],
      "credits": 3,
      "passrate": 0.0
    },
    {
      "name": "ANTH452",
      "term": 11,
      "prerequisites": [
        "WRI122"
      ],
      "corequisites": [

      ],
      "credits": 3,
      "passrate": 0.0
    },
    {
      "name": "BUS447",
      "term": 11,
      "prerequisites": [
        "BUS215",
        "PSY347",
        "WRI122"
      ],
      "corequisites": [

      ],
      "credits": 3,
      "passrate": 0.0
    },
    {
      "name": "BUS496",
      "term": 11,
      "prerequisites": [
        "BUS495"
      ],
      "corequisites": [

      ],
      "credits": 2,
      "passrate": 0.0
    },
    {
      "name": "ELEC",
      "term": 11,
      "prerequisites": [

      ],
      "corequisites": [

      ],
      "credits": 3,
      "passrate": 0.0
    },
    {
      "name": "ELEC",
      "term": 11,
      "prerequisites": [

      ],
      "corequisites": [

      ],
      "credits": 3,
      "passrate": 0.0
    },
    {
      "name": "BUS434",
      "term": 12,
      "prerequisites": [
        "BUS223",
        "BUS308"
      ],
      "corequisites": [

      ],
      "credits": 3,
      "passrate": 0.0
    },
    {
      "name": "BUS442",
      "term": 12,
      "prerequisites": [
        "BUS441"
      ],
      "corequisites": [

      ],
      "credits": 3,
      "passrate": 0.0
    },
    {
      "name": "BUS478",
      "term": 12,
      "prerequisites": [
        "ACC203",
        "WRI227"
      ],
      "corequisites": [

      ],
      "credits": 3,
      "passrate": 0.0
    },
    {
      "name": "BUS497",
      "term": 12,
      "prerequisites": [
        "BUS496"
      ],
      "corequisites": [
        "BUS356"
      ],
      "credits": 3,
      "passrate": 0.0
    }
  ],
  "terms": 12
}